pybunch/__init__.py
pybunch/__main__.py
pybunch/cli.py
pybunch/packed_base.py
pybunch/project.py
pybunch-1.1.3.dist-info/licenses/LICENSE
pybunch-1.1.3.dist-info/METADATA
pybunch-1.1.3.dist-info/WHEEL
pybunch-1.1.3.dist-info/entry_points.txt
pybunch-1.1.3.dist-info/top_level.txt
pybunch-1.1.3.dist-info/RECORD
