Metadata-Version: 2.4
Name: pybunch
Version: 1.1.3
Summary: A python utility to pack python projects into a single python file
Author-email: Yonatan Karidi <ykaridi@gmail.com>
Project-URL: Homepage, https://github.com/ykaridi/pybunch
Project-URL: Issues, https://github.com/ykaridi/pybunch/issues
Classifier: Programming Language :: Python :: 3
Classifier: License :: OSI Approved :: MIT License
Classifier: Operating System :: OS Independent
Requires-Python: >=3.8
License-File: LICENSE
Requires-Dist: argparse>=1.0.0
Dynamic: license-file
